adaptive_pipeline/__init__.py
adaptive_pipeline/_adaptive_pipeline_cache_impl.cp313-win_amd64.pyd
adaptive_pipeline/adaptive_pipeline_impl.pyi
adaptive_pipeline/cache.py
adaptive_pipeline/config.json
adaptive_pipeline/py.typed
adaptive_pipeline-0.1.5.dist-info/METADATA
adaptive_pipeline-0.1.5.dist-info/WHEEL
adaptive_pipeline-0.1.5.dist-info/licenses/LICENSE
adaptive_pipeline-0.1.5.dist-info/RECORD
