Metadata-Version: 2.2
Name: adaptive-pipeline
Version: 0.1.5
Summary: An adaptive Pipeline Cache composed of FIFO and upgraded TinyLFU with cost-awareness
Keywords: cache,pipeline,performance,cpp,lru,lfu,fifo,adaptive
Author-Email: Nadav Keren <nadavker@pm.me>
License: MIT
Classifier: Development Status :: 4 - Beta
Classifier: Intended Audience :: Developers
Classifier: License :: OSI Approved :: MIT License
Classifier: Operating System :: OS Independent
Classifier: Programming Language :: Python :: 3
Classifier: Programming Language :: Python :: 3.8
Classifier: Programming Language :: Python :: 3.9
Classifier: Programming Language :: Python :: 3.10
Classifier: Programming Language :: Python :: 3.11
Classifier: Programming Language :: Python :: 3.12
Classifier: Programming Language :: Python :: 3.13
Classifier: Programming Language :: C++
Classifier: Topic :: Software Development :: Libraries :: Python Modules
Classifier: Typing :: Typed
Project-URL: Homepage, https://github.com/NadavKeren/python-adaptive-pipeline-cache
Project-URL: Repository, https://github.com/NadavKeren/python-adaptive-pipeline-cache
Project-URL: Issues, https://github.com/NadavKeren/python-adaptive-pipeline-cache/issues
Requires-Python: >=3.8
Requires-Dist: pybind11>=2.6.0
